{
  "seoTitle": "galaxycore新闻动态 | distributor最新资讯",
  "seoDescription": "galaxycore最新产品发布、行业动态，distributor为您带来前沿资讯。",
  "seoKeywords": [
    "galaxycore 新闻",
    "galaxycore distributor",
    "产品发布",
    "行业动态"
  ],
  "articles": [
    {
      "id": "news-001",
      "title": "galaxycore发布新一代产品",
      "slug": "galaxycore-new-product-launch",
      "date": "2026-04-03",
      "summary": "新产品发布摘要",
      "content": "新闻内容...",
      "image": "/images/news/galaxycore/news-001.jpg",
      "tags": [
        "新品发布",
        "技术创新"
      ]
    }
  ]
}